Workbook
Name DiscountRate: Assumptions!$B$2
Name TerminalGrowth: Assumptions!$B$3
Name TaxRate: Assumptions!$B$4

Sheet Inputs
A1: Quarterly Revenue (Source: Bloomberg)
B2: 100.61 | C2: 98.53 | D2: 100.03 | E2: 101.91 | F2: 98.01 | G2: 95.41 | H2: 95.66 | I2: 95.03 | J2: 94.99 | K2: 93.29 | L2: 95.05 | M2: 96.6
A3: Quarterly Costs
B4: 60.45 | C4: 59.2 | D4: 60.1 | E4: 61.23 | F4: 58.89 | G4: 57.33 | H4: 57.48 | I4: 57.1 | J4: 57.08 | K4: 56.06 | L4: 57.11 | M4: 58.04
A6: Growth Rates
B7: 0 | C7: -0.0207 | D7: 0.0152 | E7: 0.0188 | F7: -0.0383 | G7: -0.0265 | H7: 0.0026 | I7: -0.0066 | J7: -0.0004 | K7: -0.0179 | L7: 0.0189 | M7: 0.0163
A9: Volume Data
B10: 5000 | C10: 5015 | D10: 5001 | E10: 4957 | F10: 4934 | G10: 4884 | H10: 4887 | I10: 4954 | J10: 4930 | K10: 4899 | L10: 4923 | M10: 4941

Sheet Assumptions
A1: Parameter | B1: Value
A2: Discount Rate | B2: 0.08
A3: Terminal Growth Rate | B3: 0.025
A4: Tax Rate | B4: 0.21
A5: Inflation Rate | B5: 0.03

Sheet Calculations
A1: Metric
A2: Gross Profit | B2: =Inputs!B2-Inputs!B4 | C2: =Inputs!C2-Inputs!C4 | D2: =Inputs!D2-Inputs!D4 | E2: =Inputs!E2-Inputs!E4 | F2: =Inputs!F2-Inputs!F4 | G2: =Inputs!G2-Inputs!G4 | H2: =Inputs!H2-Inputs!H4 | I2: =Inputs!I2-Inputs!I4 | ... M2: =Inputs!M2-Inputs!M4
A3: Tax Amount | B3: =B2*Assumptions!$B$4 | C3: =C2*Assumptions!$B$4 | D3: =D2*Assumptions!$B$4 | E3: =E2*Assumptions!$B$4 | F3: =F2*Assumptions!$B$4 | G3: =G2*Assumptions!$B$4 | H3: =H2*Assumptions!$B$4 | I3: =I2*Assumptions!$B$4 | ... M3: =M2*Assumptions!$B$4
A4: Net Income | B4: =B2-B3 | C4: =C2-C3 | D4: =D2-D3 | E4: =E2-E3 | F4: =F2-F3 | G4: =G2-G3 | H4: =H2-H3 | I4: =I2-I3 | ... M4: =M2-M3
A5: Discounted Cash Flow | B5: =B4/(1+Assumptions!$B$2)^1 | C5: =C4/(1+Assumptions!$B$2)^2 | D5: =D4/(1+Assumptions!$B$2)^3 | E5: =E4/(1+Assumptions!$B$2)^4 | F5: =F4/(1+Assumptions!$B$2)^5 | G5: =G4/(1+Assumptions!$B$2)^6 | H5: =H4/(1+Assumptions!$B$2)^7 | I5: =I4/(1+Assumptions!$B$2)^8 | J5: =J4/(1+Assumptions!$B$2)^9 | K5: =K4/(1+Assumptions!$B$2)^10 | L5: =L4/(1+Assumptions!$B$2)^11 | M5: =M4/(1+Assumptions!$B$2)^12
A6: Cumulative DCF | B6: =B5 | C6: =B6+C5 | D6: =C6+D5 | E6: =D6+E5 | F6: =E6+F5 | G6: =F6+G5 | H6: =G6+H5 | I6: =H6+I5 | J6: =I6+J5 | ... M6: =L6+M5
N3: ='[upstream_a.xlsx]'!QuarterlyRevenue -> 0

Sheet Summary
A1: Summary Output
A3: Total Revenue | B3: =SUM(Inputs!B2:M2)
A4: Total Costs | B4: =SUM(Inputs!B4:M4)
A5: Total Gross Profit | B5: =SUM(Calculations!B2:M2)
A6: Total Net Income | B6: =SUM(Calculations!B4:M4)
A7: NPV (Sum of DCF) | B7: =SUM(Calculations!B5:M5)
A8: Terminal Value | B8: =Calculations!M4*(1+Assumptions!B3)/(Assumptions!B2-Assumptions!B3)
A9: Enterprise Value | B9: =B7+B8
A10: Discount Rate Used | B10: =Assumptions!B2
A11: Avg Growth Rate | B11: =AVERAGE(Inputs!B7:M7)
